{
  "latest_version": "0.5.5",
  "min_supported_version": "0.1.0",
  "release_notes": "完善磁盘读取功能",
  "release_date": "2026-03-19",
  "download_url": "https://files.xiaozhi.me/tenbox/releases/TenBox_0.5.5.msi",
  "sha256": "85191054d883684f89f634e412edd07f2f8cc9fc5b7ccb8406bdd952bff66f99",
  "platforms": {
    "windows": {
      "latest_version": "0.5.5",
      "release_notes": "完善磁盘读取功能",
      "release_date": "2026-03-19",
      "download_url": "https://files.xiaozhi.me/tenbox/releases/TenBox_0.5.5.msi",
      "sha256": "85191054d883684f89f634e412edd07f2f8cc9fc5b7ccb8406bdd952bff66f99",
      "size": 3231744,
      "min_os": "Windows 10"
    },
    "macos": {
      "latest_version": "0.5.6",
      "release_notes": "激活窗体时自动同步时间",
      "release_date": "2026-03-20",
      "download_url": "https://files.xiaozhi.me/tenbox/releases/TenBox-0.5.6.dmg",
      "sha256": "0ab61697a5046517efa5e8eab271f28f7823cfc11489b418968de1b46a859f01",
      "size": 4543240,
      "min_os": "macOS 12"
    }
  }
}
